gcdlcm/__init__.py
gcd_lcm_calculator-1.0.2.dist-info/METADATA
gcd_lcm_calculator-1.0.2.dist-info/WHEEL
gcd_lcm_calculator-1.0.2.dist-info/top_level.txt
gcd_lcm_calculator-1.0.2.dist-info/RECORD
