Metadata-Version: 2.2
Name: gcd-lcm-calculator
Version: 1.0.2
Summary: You can find the gcm (greatest common divisior) and lcm (least command multiplier) of the numbers. And also you can find the other values of the primity.
Home-page: https://github.com/burakcanturk/Quectel-5G-LTE-Module-Library.git
Author: Burak Cantürk
Author-email: burakcanturk12@gmail.com
Classifier: Programming Language :: Python :: 3
Classifier: License :: OSI Approved :: MIT License
Classifier: Operating System :: OS Independent
Dynamic: author
Dynamic: author-email
Dynamic: classifier
Dynamic: description
Dynamic: description-content-type
Dynamic: home-page
Dynamic: summary
